{
  "errCode": "200",
  "errMsg": null,
  "payload": {
    "menus": [{
      "children": [{
        "children": [{
          "children": [],
          "title": "测试子部门",
          "key": "334521465"
        }],
        "title": "测试部门",
        "key": "334987347"
      }, {
        "children": [{
          "children": [{
            "children": [{
              "children": [{
                "children": [],
                "title": "民警",
                "key": "80615783"
              }],
              "title": "西湖派出所",
              "key": "73313046"
            }, {
              "children": [{
                "children": [{
                  "children": [],
                  "title": "社区1",
                  "key": "73266047"
                }, {
                  "children": [],
                  "title": "社区2",
                  "key": "73277047"
                }],
                "title": "民警",
                "key": "73178077"
              }],
              "title": "文新派出所",
              "key": "73294046"
            }],
            "title": "分局部门",
            "key": "73207054"
          }],
          "title": "网格化管理",
          "key": "73240049"
        }, {
          "children": [{
            "children": [{
              "children": [{
                "children": [{
                  "children": [{
                    "children": [],
                    "title": "文新社区",
                    "key": "98410264"
                  }],
                  "title": "民警",
                  "key": "97295163"
                }],
                "title": "文新派出所",
                "key": "97261196"
              }, {
                "children": [{
                  "children": [{
                    "children": [],
                    "title": "东新园社区",
                    "key": "98426560"
                  }, {
                    "children": [],
                    "title": "中州社区",
                    "key": "98452451"
                  }],
                  "title": "民警",
                  "key": "98646533"
                }],
                "title": "东新派出所",
                "key": "98451573"
              }],
              "title": "分局部门",
              "key": "97236197"
            }],
            "title": "网格化管理",
            "key": "94931036"
          }, {
            "children": [{
              "children": [{
                "children": [{
                  "children": [{
                    "children": [],
                    "title": "新华坊社区",
                    "key": "98371423"
                  }],
                  "title": "长庆派出所",
                  "key": "98557457"
                }, {
                  "children": [{
                    "children": [],
                    "title": "石桥社区",
                    "key": "98591275"
                  }],
                  "title": "王石桥派出所",
                  "key": "98606233"
                }, {
                  "children": [],
                  "title": "华联派出所",
                  "key": "108481847"
                }, {
                  "children": [],
                  "title": "风起派出所",
                  "key": "108590461"
                }, {
                  "children": [],
                  "title": "安吉派出所",
                  "key": "108670760"
                }, {
                  "children": [],
                  "title": "兰博派出所",
                  "key": "108690859"
                }, {
                  "children": [],
                  "title": "山药派出所",
                  "key": "108701774"
                }, {
                  "children": [{
                    "children": [],
                    "title": "社区A",
                    "key": "115594068"
                  }],
                  "title": "派出所G",
                  "key": "115331745"
                }, {
                  "children": [{
                    "children": [],
                    "title": "社区C",
                    "key": "115547069"
                  }],
                  "title": "派出所C",
                  "key": "115354955"
                }, {
                  "children": [{
                    "children": [],
                    "title": "社区G",
                    "key": "115539104"
                  }],
                  "title": "派出所A",
                  "key": "115363622"
                }, {
                  "children": [{
                    "children": [],
                    "title": "社区E",
                    "key": "115601083"
                  }],
                  "title": "派出所E",
                  "key": "115579054"
                }, {
                  "children": [{
                    "children": [],
                    "title": "社区F",
                    "key": "115547070"
                  }],
                  "title": "派出所F",
                  "key": "115617067"
                }, {
                  "children": [{
                    "children": [],
                    "title": "社区D",
                    "key": "115341741"
                  }],
                  "title": "派出所D",
                  "key": "115638047"
                }, {
                  "children": [{
                    "children": [],
                    "title": "社区B",
                    "key": "115528084"
                  }],
                  "title": "派出所B",
                  "key": "115640058"
                }],
                "title": "特警（一级）",
                "key": "98483297"
              }],
              "title": "分局防控中心",
              "key": "98461215"
            }],
            "title": "四级巡防",
            "key": "95012042"
          }, {
            "children": [{
              "children": [{
                "children": [{
                  "children": [{
                    "children": [],
                    "title": "调解员",
                    "key": "98636261"
                  }],
                  "title": "民警",
                  "key": "98626273"
                }],
                "title": "所领导",
                "key": "98624330"
              }],
              "title": "三级派出所",
              "key": "98458265"
            }],
            "title": "三级警调",
            "key": "95156042"
          }],
          "title": "西湖分局群众力量",
          "key": "95042030"
        }],
        "title": "西湖分局",
        "key": "73313045"
      }, {
        "children": [{
          "children": [{
            "children": [{
              "children": [{
                "children": [{
                  "children": [],
                  "title": "社会力量",
                  "key": "72329531"
                }],
                "title": "调解员",
                "key": "72370407"
              }],
              "title": "民警",
              "key": "72437425"
            }, {
              "children": [],
              "title": "测试部门",
              "key": "74519423"
            }],
            "title": "所领导",
            "key": "72265310"
          }],
          "title": "三级警调",
          "key": "72308200"
        }, {
          "children": [{
            "children": [{
              "children": [],
              "title": "民警",
              "key": "72308352"
            }, {
              "children": [{
                "children": [],
                "title": "网格B",
                "key": "72250380"
              }, {
                "children": [],
                "title": "网格A",
                "key": "72396325"
              }],
              "title": "社区A",
              "key": "72349373"
            }, {
              "children": [{
                "children": [],
                "title": "网格B1",
                "key": "72396415"
              }],
              "title": "社区B",
              "key": "72304308"
            }],
            "title": "所领导",
            "key": "72257422"
          }],
          "title": "网格化管理",
          "key": "72431323"
        }, {
          "children": [{
            "children": [{
              "children": [{
                "children": [],
                "title": "社区A",
                "key": "72392457"
              }, {
                "children": [],
                "title": "社区B",
                "key": "72433360"
              }],
              "title": "村社",
              "key": "72353306"
            }, {
              "children": [],
              "title": "社会巡防",
              "key": "72339526"
            }],
            "title": "派出所",
            "key": "72489400"
          }],
          "title": "四级巡防",
          "key": "72364177"
        }, {
          "children": [],
          "title": "民警",
          "key": "72283445"
        }],
        "title": "西湖派出所",
        "key": "72433197"
      }, {
        "children": [],
        "title": "劳拉贵族学校",
        "key": "367925001"
      }, {
        "children": [{
          "children": [],
          "title": "测试111部",
          "key": "364902439"
        }, {
          "children": [],
          "title": "测试11部",
          "key": "365120113"
        }],
        "title": "测试1部",
        "key": "136320672"
      }, {
        "children": [{
          "children": [],
          "title": "网格B",
          "key": "72022916"
        }, {
          "children": [{
            "children": [{
              "children": [],
              "title": "网格A",
              "key": "72088587"
            }, {
              "children": [],
              "title": "社会力量",
              "key": "72103833"
            }],
            "title": "文新社区",
            "key": "72140558"
          }, {
            "children": [{
              "children": [],
              "title": "网格B",
              "key": "71990780"
            }, {
              "children": [],
              "title": "网格A",
              "key": "72187878"
            }, {
              "children": [],
              "title": "社区力量",
              "key": "72216055"
            }],
            "title": "五常社区",
            "key": "72167569"
          }],
          "title": "社区",
          "key": "72165630"
        }],
        "title": "民警",
        "key": "72199544"
      }, {
        "children": [{
          "children": [],
          "title": "油管2部",
          "key": "136251931"
        }, {
          "children": [],
          "title": "网格化管理",
          "key": "77701304"
        }, {
          "children": [{
            "children": [{
              "children": [{
                "children": [{
                  "children": [],
                  "title": "调解员",
                  "key": "98638432"
                }],
                "title": "所领导",
                "key": "98458408"
              }],
              "title": "西湖派出所",
              "key": "95025065"
            }],
            "title": "三级警调",
            "key": "94956037"
          }, {
            "children": [],
            "title": "网格化管理",
            "key": "94965024"
          }, {
            "children": [{
              "children": [],
              "title": "特警一",
              "key": "102755100"
            }],
            "title": "四级巡防",
            "key": "95032052"
          }],
          "title": "萧山分局群众力量",
          "key": "94950047"
        }],
        "title": "萧山分局",
        "key": "77847241"
      }, {
        "children": [{
          "children": [],
          "title": "油管1部",
          "key": "136184795"
        }],
        "title": "定制组开发团队",
        "key": "77866776"
      }, {
        "children": [{
          "children": [{
            "children": [{
              "children": [{
                "children": [{
                  "children": [],
                  "title": "二里地保安",
                  "key": "73135155"
                }, {
                  "children": [],
                  "title": "三里屯保安",
                  "key": "73146107"
                }],
                "title": "海丽社区",
                "key": "73332115"
              }],
              "title": "古荡派出所",
              "key": "73153139"
            }, {
              "children": [{
                "children": [{
                  "children": [],
                  "title": "金都花园保安",
                  "key": "73232139"
                }, {
                  "children": [],
                  "title": "金城花园保安",
                  "key": "73252107"
                }],
                "title": "文新古墩社区",
                "key": "73156131"
              }],
              "title": "文新派出所",
              "key": "73185117"
            }],
            "title": "特警",
            "key": "73242144"
          }],
          "title": "领导",
          "key": "73324139"
        }],
        "title": "四级巡防",
        "key": "72262006"
      }, {
        "children": [{
          "children": [],
          "title": "温州市电大",
          "key": "80549137"
        }, {
          "children": [{
            "children": [],
            "title": "余杭区电大",
            "key": "80559100"
          }, {
            "children": [],
            "title": "萧山区电大",
            "key": "80722121"
          }],
          "title": "杭州市电大",
          "key": "80660155"
        }, {
          "children": [],
          "title": "校领导",
          "key": "84563553"
        }],
        "title": "省电大",
        "key": "80750160"
      }, {
        "children": [{
          "children": [],
          "title": "网格化管理",
          "key": "84591273"
        }],
        "title": "奇点科技",
        "key": "84633222"
      }, {
        "children": [],
        "title": "电大测试",
        "key": "86091173"
      }, {
        "children": [{
          "children": [{
            "children": [],
            "title": "1.2.1",
            "key": "93645228"
          }, {
            "children": [],
            "title": "1.2.2",
            "key": "93637200"
          }, {
            "children": [],
            "title": "1.2.3",
            "key": "93827190"
          }],
          "title": "1.2",
          "key": "93637199"
        }, {
          "children": [],
          "title": "1.5",
          "key": "93848204"
        }],
        "title": "1",
        "key": "93720231"
      }, {
        "children": [{
          "children": [],
          "title": "景区部门",
          "key": "94515398"
        }, {
          "children": [],
          "title": "民警",
          "key": "94544247"
        }],
        "title": "景区分局",
        "key": "94254729"
      }, {
        "children": [{
          "children": [{
            "children": [{
              "children": [{
                "children": [],
                "title": "社区A",
                "key": "77957319"
              }],
              "title": "民警",
              "key": "77918260"
            }],
            "title": "新塘派出所",
            "key": "77988277"
          }],
          "title": "分局部门",
          "key": "77743278"
        }, {
          "children": [],
          "title": "民警",
          "key": "94313422"
        }, {
          "children": [],
          "title": "桐庐部门",
          "key": "94486354"
        }],
        "title": "桐庐县分局",
        "key": "94284719"
      }, {
        "children": [{
          "children": [],
          "title": "民警",
          "key": "94251554"
        }, {
          "children": [],
          "title": "余杭部门",
          "key": "94253555"
        }],
        "title": "余杭分局",
        "key": "94294525"
      }, {
        "children": [{
          "children": [],
          "title": "民警",
          "key": "94351792"
        }, {
          "children": [],
          "title": "滨江部门",
          "key": "94550296"
        }],
        "title": "滨江分局",
        "key": "94324647"
      }, {
        "children": [{
          "children": [{
            "children": [],
            "title": "定制公安后端开发5.11",
            "key": "344692625"
          }],
          "title": "民警",
          "key": "94262497"
        }, {
          "children": [],
          "title": "建德部门",
          "key": "94409394"
        }],
        "title": "建德市分局",
        "key": "94330477"
      }, {
        "children": [{
          "children": [],
          "title": "下城部门",
          "key": "94247653"
        }, {
          "children": [],
          "title": "民警",
          "key": "94470348"
        }],
        "title": "下城分局",
        "key": "94349508"
      }, {
        "children": [{
          "children": [],
          "title": "民警",
          "key": "94461334"
        }, {
          "children": [],
          "title": "大江东部门",
          "key": "94517315"
        }],
        "title": "大江东分局",
        "key": "94334454"
      }, {
        "children": [{
          "children": [],
          "title": "淳安部门",
          "key": "94495292"
        }, {
          "children": [],
          "title": "民警",
          "key": "94502332"
        }],
        "title": "淳安县分局",
        "key": "94355532"
      }, {
        "children": [{
          "children": [],
          "title": "民警",
          "key": "94460379"
        }, {
          "children": [],
          "title": "上城部门",
          "key": "94514280"
        }],
        "title": "上城分局",
        "key": "94370509"
      }, {
        "children": [{
          "children": [],
          "title": "江干部门",
          "key": "94331419"
        }, {
          "children": [],
          "title": "民警",
          "key": "94386392"
        }],
        "title": "江干分局",
        "key": "94404425"
      }, {
        "children": [{
          "children": [],
          "title": "民警",
          "key": "94244661"
        }, {
          "children": [],
          "title": "富阳部门",
          "key": "94453384"
        }],
        "title": "富阳分局",
        "key": "94412483"
      }, {
        "children": [{
          "children": [],
          "title": "开发区部门",
          "key": "94357400"
        }, {
          "children": [],
          "title": "民警",
          "key": "94358441"
        }],
        "title": "开发区分局",
        "key": "94427467"
      }, {
        "children": [{
          "children": [],
          "title": "拱墅部门",
          "key": "94265505"
        }, {
          "children": [],
          "title": "民警",
          "key": "94533351"
        }],
        "title": "拱墅分局",
        "key": "94433368"
      }, {
        "children": [{
          "children": [],
          "title": "民警",
          "key": "94357401"
        }, {
          "children": [],
          "title": "临安部门",
          "key": "94434556"
        }],
        "title": "临安分局",
        "key": "94480367"
      }, {
        "children": [],
        "title": "心怡科技",
        "key": "98979030"
      }, {
        "children": [{
          "children": [],
          "title": "玉环学院",
          "key": "102609825"
        }],
        "title": "台州地区",
        "key": "102609822"
      }, {
        "children": [{
          "children": [],
          "title": "杭州电大",
          "key": "102609824"
        }],
        "title": "杭州地区",
        "key": "102609823"
      }, {
        "children": [{
          "children": [{
            "children": [{
              "children": [],
              "title": "浙江大学委员会玉泉总支第一支部",
              "key": "107674290"
            }],
            "title": "玉泉总支",
            "key": "107658301"
          }],
          "title": "浙江大学委员会",
          "key": "107672218"
        }],
        "title": "省直工委",
        "key": "107583234"
      }, {
        "children": [{
          "children": [{
            "children": [],
            "title": "萧山文化支部",
            "key": "107743192"
          }],
          "title": "萧山区委会",
          "key": "107582251"
        }],
        "title": "杭州市委会",
        "key": "107808277"
      }, {
        "children": [],
        "title": "门禁测试",
        "key": "117066321"
      }, {
        "children": [{
          "children": [],
          "title": "0104*前期部",
          "key": "125423589"
        }, {
          "children": [{
            "children": [],
            "title": "010303*扩展子部门",
            "key": "127898189"
          }],
          "title": "0103*拓展部",
          "key": "125433596"
        }, {
          "children": [],
          "title": "0107*营销部",
          "key": "125511612"
        }, {
          "children": [],
          "title": "0102*财务部",
          "key": "125528626"
        }, {
          "children": [],
          "title": "G0108*叠翠湾项目公司",
          "key": "125568610"
        }, {
          "children": [],
          "title": "0105*设计部",
          "key": "125609674"
        }, {
          "children": [],
          "title": "G0110*永福项目公司",
          "key": "125647598"
        }, {
          "children": [],
          "title": "0106*工程部",
          "key": "125651609"
        }, {
          "children": [],
          "title": "0101*办公室",
          "key": "125705521"
        }, {
          "children": [],
          "title": "G0109*五常项目公司",
          "key": "125710536"
        }],
        "title": "G01*中宙投资",
        "key": "124269041"
      }, {
        "children": [{
          "children": [{
            "children": [],
            "title": "上城区",
            "key": "152588123"
          }],
          "title": "产品创新部门",
          "key": "152186919"
        }, {
          "children": [],
          "title": "商务通开发",
          "key": "232596461"
        }],
        "title": "开发中心",
        "key": "151300400"
      }, {
        "children": [{
          "children": [{
            "children": [],
            "title": "余杭支队租客群2",
            "key": "276921627"
          }, {
            "children": [],
            "title": "余杭支队租客群",
            "key": "279055248"
          }],
          "title": "余杭支队",
          "key": "127624411"
        }, {
          "children": [{
            "children": [],
            "title": "西湖支队租客群",
            "key": "279135486"
          }],
          "title": "西湖支队",
          "key": "127625258"
        }, {
          "children": [],
          "title": "杭州支局",
          "key": "130307220"
        }],
        "title": "杭州消防",
        "key": "127395111"
      }, {
        "children": [],
        "title": "从文测试勿动",
        "key": "265084210"
      }, {
        "children": [],
        "title": "从文测试勿动2",
        "key": "265314134"
      }, {
        "children": [],
        "title": "商务通2",
        "key": "270618080"
      }, {
        "children": [],
        "title": "商务通3",
        "key": "270626107"
      }, {
        "children": [],
        "title": "商务通1",
        "key": "270816042"
      }, {
        "children": [{
          "children": [],
          "title": "商务通4子部门",
          "key": "339070612"
        }],
        "title": "商务通4",
        "key": "281050235"
      }, {
        "children": [],
        "title": "开发合作伙伴",
        "key": "311968753"
      }, {
        "children": [{
          "children": [],
          "title": "1",
          "key": "402683786"
        }],
        "title": "米雪测试",
        "key": "370729024"
      }, {
        "children": [],
        "title": "业务实施",
        "key": "380868796"
      }],
      "title": "订制团队开发",
      "key": "1"
    }]
  },
  "succeed": true
}